thescheduler/__init__.py
thescheduler/thescheduler.py
thescheduler-0.1.0.dist-info/AUTHORS.rst
thescheduler-0.1.0.dist-info/LICENSE
thescheduler-0.1.0.dist-info/METADATA
thescheduler-0.1.0.dist-info/WHEEL
thescheduler-0.1.0.dist-info/top_level.txt
thescheduler-0.1.0.dist-info/RECORD
