Metadata-Version: 2.1
Name: thescheduler
Version: 0.1.0
Summary: A distributed declarative task scheduler built on Celery
Home-page: https://github.com/ehm-are/thescheduler
Author: M Rahman
Author-email: mmr@twostations.com
License: MPL 2.0
Keywords: thescheduler,celery,redis,scheduler,task,job,distributed,messaging
Platform: UNKNOWN
Classifier: Development Status :: 2 - Pre-Alpha
Classifier: Intended Audience :: Developers
Classifier: License :: OSI Approved :: Mozilla Public License 2.0 (MPL 2.0)
Classifier: Natural Language :: English
Classifier: Programming Language :: Python :: 2
Classifier: Programming Language :: Python :: 2.7
Classifier: Programming Language :: Python :: 3
Classifier: Programming Language :: Python :: 3.4
Classifier: Programming Language :: Python :: 3.5
Classifier: Programming Language :: Python :: 3.6
Classifier: Programming Language :: Python :: 3.7
